lambda_handlers/__init__.py
lambda_handlers/errors.py
lambda_handlers/types.py
lambda_handlers/version.py
lambda_handlers/formatters/__init__.py
lambda_handlers/formatters/format.py
lambda_handlers/formatters/input_format.py
lambda_handlers/formatters/output_format.py
lambda_handlers/handlers/__init__.py
lambda_handlers/handlers/event_handler.py
lambda_handlers/handlers/http_handler.py
lambda_handlers/handlers/lambda_handler.py
lambda_handlers/handlers/mixins/__init__.py
lambda_handlers/handlers/mixins/formatting_mixin.py
lambda_handlers/response/__init__.py
lambda_handlers/response/cors_headers.py
lambda_handlers/response/response_builder.py
lambda_handlers-3.0.8.dist-info/LICENSE
lambda_handlers-3.0.8.dist-info/METADATA
lambda_handlers-3.0.8.dist-info/WHEEL
lambda_handlers-3.0.8.dist-info/top_level.txt
lambda_handlers-3.0.8.dist-info/RECORD
