Metadata-Version: 2.1
Name: lambda-handlers
Version: 3.0.8
Summary: A collection of useful decorators for making AWS Lambda handlers
Home-page: UNKNOWN
Author: Steffen Leistner, Alexandre Savio
Author-email: info@enterat.de
License: Apache License Version 2.0
Project-URL: Documentation, http://lambda-handlers.readthedocs.io
Project-URL: Source Code, https://github.com/enter-at/lambda-handlers
Project-URL: Bug Tracker, https://github.com/enter-at/lambda-handlers/issues
Project-URL: Changelog, https://github.com/enter-at/lambda-handlers/blob/master/CHANGELOG.md
Keywords: aws,lambda,serverless,decorator,http,api,rest,json,validation
Platform: UNKNOWN
Classifier: Development Status :: 5 - Production/Stable
Classifier: Environment :: Other Environment
Classifier: Intended Audience :: Developers
Classifier: License :: OSI Approved :: Apache Software License
Classifier: Programming Language :: Python :: 3
Classifier: Programming Language :: Python :: 3.7
Requires-Python: >=3.7
